greeking/__init__.py
greeking/apps.py
greeking/jabberwocky.py
greeking/latimes_ipsum.py
greeking/models.py
greeking/pangrams.py
greeking/placekittens.py
greeking/quotables.py
greeking/tests.py
greeking/templatetags/__init__.py
greeking/templatetags/greeking_tags.py
greeking-4.0.1.dist-info/LICENSE
greeking-4.0.1.dist-info/METADATA
greeking-4.0.1.dist-info/WHEEL
greeking-4.0.1.dist-info/top_level.txt
greeking-4.0.1.dist-info/RECORD
