Metadata-Version: 2.1
Name: greeking
Version: 4.0.1
Summary: Django template tools for printing filler, a technique from the days of hot type known as greeking
Home-page: https://palewi.re/docs/django-greeking/
Author: Ben Welsh
Author-email: b@palewi.re
License: MIT
Project-URL: Documentation, https://palewi.re/docs/django-greeking/
Project-URL: Source, https://github.com/datadesk/django-greeking/
Project-URL: Tracker, https://github.com/datadesk/django-greeking/issues
Keywords: greeking pangrams lorem ipsum quotables comments text jabberwocky placekittens fillmurray filler
Classifier: Development Status :: 5 - Production/Stable
Classifier: Intended Audience :: Developers
Classifier: Intended Audience :: Science/Research
Classifier: License :: OSI Approved :: MIT License
Classifier: Operating System :: OS Independent
Classifier: Programming Language :: Python
Classifier: Programming Language :: Python :: 3
Classifier: Programming Language :: Python :: 3.7
Classifier: Programming Language :: Python :: 3.8
Classifier: Programming Language :: Python :: 3.9
Classifier: Programming Language :: Python :: 3.10
Classifier: Programming Language :: Python :: 3.11
Classifier: Framework :: Django
Classifier: Topic :: Software Development :: Libraries :: Python Modules
License-File: LICENSE
